detect_service/Anomaly_Model_Training_Service.py
detect_service/__init__.py
Anomaly_Model-1.8.2.dist-info/METADATA
Anomaly_Model-1.8.2.dist-info/WHEEL
Anomaly_Model-1.8.2.dist-info/top_level.txt
Anomaly_Model-1.8.2.dist-info/RECORD
